[
  {"pokemon": "アイアント", "needAllBall": "3"},
  {"pokemon": "アゴジムシ", "needAllBall": "3"},
  {"pokemon": "アブリー", "needAllBall": "3"},
  {"pokemon": "アマカジ", "needAllBall": "2"},
  {"pokemon": "イーブイ", "needAllBall": "3"},
  {"pokemon": "イエッサン", "needAllBall": "3"},
  {"pokemon": "イシズマイ", "needAllBall": "3"},
  {"pokemon": "イシヘンジン", "needAllBall": "3"},
  {"pokemon": "イワーク", "needAllBall": "3"},
  {"pokemon": "ウールー", "needAllBall": "3"},
  {"pokemon": "ウソッキー", "needAllBall": "3"},
  {"pokemon": "ウッウ", "needAllBall": "3"},
  {"pokemon": "ウパー", "needAllBall": "3"},
  {"pokemon": "ウリムー", "needAllBall": "3"},
  {"pokemon": "エリキテル", "needAllBall": "3"},
  {"pokemon": "エレズン", "needAllBall": "3"},
  {"pokemon": "オタマロ", "needAllBall": "3"},
  {"pokemon": "オンバット", "needAllBall": "3"},
  {"pokemon": "ガーディ", "needAllBall": "3"},
  {"pokemon": "カジッチュ", "needAllBall": "3"},
  {"pokemon": "カチコール", "needAllBall": "3"},
  {"pokemon": "カビゴン", "needAllBall": "3"},
  {"pokemon": "カブルモ", "needAllBall": "3"},
  {"pokemon": "カムカメ", "needAllBall": "3"},
  {"pokemon": "カメテテ", "needAllBall": "3"},
  {"pokemon": "カモネギ", "needAllBall": "3"},
  {"pokemon": "カラナクシ", "needAllBall": "3"},
  {"pokemon": "ギアル", "needAllBall": "0"},
  {"pokemon": "キバゴ", "needAllBall": "3"},
  {"pokemon": "キャタピー", "needAllBall": "3"},
  {"pokemon": "キャモメ", "needAllBall": "3"},
  {"pokemon": "クイタラン", "needAllBall": "3"},
  {"pokemon": "クスネ", "needAllBall": "3"},
  {"pokemon": "クチート", "needAllBall": "3"},
  {"pokemon": "クマシュン", "needAllBall": "3"},
  {"pokemon": "クラブ", "needAllBall": "3"},
  {"pokemon": "グレッグル", "needAllBall": "3"},
  {"pokemon": "コイキング", "needAllBall": "3"},
  {"pokemon": "ゴース", "needAllBall": "3"},
  {"pokemon": "コータス", "needAllBall": "3"},
  {"pokemon": "コオリッポ", "needAllBall": "3"},
  {"pokemon": "ココガラ", "needAllBall": "3"},
  {"pokemon": "コソクムシ", "needAllBall": "3"},
  {"pokemon": "ゴチム", "needAllBall": "3"},
  {"pokemon": "ゴビット", "needAllBall": "0"},
  {"pokemon": "コマタナ", "needAllBall": "3"},
  {"pokemon": "コロモリ", "needAllBall": "3"},
  {"pokemon": "サイホーン", "needAllBall": "3"},
  {"pokemon": "サシカマス", "needAllBall": "3"},
  {"pokemon": "サッチムシ", "needAllBall": "3"},
  {"pokemon": "サニーゴ", "needAllBall": "3"},
  {"pokemon": "シェルダー", "needAllBall": "3"},
  {"pokemon": "ジグザグマ", "needAllBall": "3"},
  {"pokemon": "ジジーロン", "needAllBall": "3"},
  {"pokemon": "シズクモ", "needAllBall": "3"},
  {"pokemon": "ジャラコ", "needAllBall": "3"},
  {"pokemon": "シュシュプ", "needAllBall": "3"},
  {"pokemon": "ジュラルドン", "needAllBall": "3"},
  {"pokemon": "シンボラー", "needAllBall": "3"},
  {"pokemon": "スカンプー", "needAllBall": "3"},
  {"pokemon": "スコルピ", "needAllBall": "3"},
  {"pokemon": "スナヘビ", "needAllBall": "3"},
  {"pokemon": "ズルッグ", "needAllBall": "3"},
  {"pokemon": "ゾウドウ", "needAllBall": "3"},
  {"pokemon": "ソーナンス", "needAllBall": "3"},
  {"pokemon": "ソルロック", "needAllBall": "0"},
  {"pokemon": "タイレーツ", "needAllBall": "0"},
  {"pokemon": "ダゲキ", "needAllBall": "1"},
  {"pokemon": "タタッコ", "needAllBall": "3"},
  {"pokemon": "ダダリン", "needAllBall": "0"},
  {"pokemon": "タネボー", "needAllBall": "3"},
  {"pokemon": "ダルマッカ", "needAllBall": "3"},
  {"pokemon": "ダンゴロ", "needAllBall": "3"},
  {"pokemon": "タンドン", "needAllBall": "3"},
  {"pokemon": "チェリンボ", "needAllBall": "3"},
  {"pokemon": "チョボマキ", "needAllBall": "3"},
  {"pokemon": "チョロネコ", "needAllBall": "3"},
  {"pokemon": "チョンチー", "needAllBall": "3"},
  {"pokemon": "チラーミィ", "needAllBall": "3"},
  {"pokemon": "ツチニン", "needAllBall": "3"},
  {"pokemon": "ツボツボ", "needAllBall": "3"},
  {"pokemon": "ディグダ", "needAllBall": "3"},
  {"pokemon": "デスマス", "needAllBall": "3"},
  {"pokemon": "テッシード", "needAllBall": "3"},
  {"pokemon": "テッポウオ", "needAllBall": "3"},
  {"pokemon": "デリバード", "needAllBall": "3"},
  {"pokemon": "ドーミラー", "needAllBall": "0"},
  {"pokemon": "ドガース", "needAllBall": "3"},
  {"pokemon": "トゲデマル", "needAllBall": "3"},
  {"pokemon": "トゲピー", "needAllBall": "3"},
  {"pokemon": "トサキント", "needAllBall": "3"},
  {"pokemon": "ドジョッチ", "needAllBall": "3"},
  {"pokemon": "ドッコラー", "needAllBall": "3"},
  {"pokemon": "ドラメシヤ", "needAllBall": "3"},
  {"pokemon": "ドロバンコ", "needAllBall": "3"},
  {"pokemon": "ナゲキ", "needAllBall": "1"},
  {"pokemon": "ナゲツケサル", "needAllBall": "3"},
  {"pokemon": "ナゾノクサ", "needAllBall": "3"},
  {"pokemon": "ナックラー", "needAllBall": "3"},
  {"pokemon": "ナマコブシ", "needAllBall": "3"},
  {"pokemon": "ニャース", "needAllBall": "3"},
  {"pokemon": "ニャスパー", "needAllBall": "3"},
  {"pokemon": "ニューラ", "needAllBall": "3"},
  {"pokemon": "ヌイコグマ", "needAllBall": "3"},
  {"pokemon": "ヌメラ", "needAllBall": "3"},
  {"pokemon": "ネイティ", "needAllBall": "3"},
  {"pokemon": "ネマシュ", "needAllBall": "3"},
  {"pokemon": "バクガメス", "needAllBall": "3"},
  {"pokemon": "バケッチャ", "needAllBall": "3"},
  {"pokemon": "ハスボー", "needAllBall": "3"},
  {"pokemon": "バスラオ", "needAllBall": "3"},
  {"pokemon": "バチュル", "needAllBall": "3"},
  {"pokemon": "バチンウニ", "needAllBall": "3"},
  {"pokemon": "バニプッチ", "needAllBall": "3"},
  {"pokemon": "ハリーセン", "needAllBall": "3"},
  {"pokemon": "バリヤード", "needAllBall": "3"},
  {"pokemon": "バルキー", "needAllBall": "1"},
  {"pokemon": "バルチャイ", "needAllBall": "2"},
  {"pokemon": "ピィ", "needAllBall": "3"},
  {"pokemon": "ピチュー", "needAllBall": "3"},
  {"pokemon": "ヒドイデ", "needAllBall": "3"},
  {"pokemon": "ヒトカゲ", "needAllBall": "3"},
  {"pokemon": "ヒトツキ", "needAllBall": "3"},
  {"pokemon": "ヒトモシ", "needAllBall": "3"},
  {"pokemon": "ヒポポタス", "needAllBall": "3"},
  {"pokemon": "ヒメンカ", "needAllBall": "3"},
  {"pokemon": "ヒンバス", "needAllBall": "3"},
  {"pokemon": "プルリル", "needAllBall": "3"},
  {"pokemon": "フワンテ", "needAllBall": "3"},
  {"pokemon": "ヘイガニ", "needAllBall": "3"},
  {"pokemon": "ペロッパフ", "needAllBall": "3"},
  {"pokemon": "ベロバー", "needAllBall": "1"},
  {"pokemon": "ホエルコ", "needAllBall": "3"},
  {"pokemon": "ホーホー", "needAllBall": "3"},
  {"pokemon": "ボクレー", "needAllBall": "3"},
  {"pokemon": "ホシガリス", "needAllBall": "3"},
  {"pokemon": "ポニータ", "needAllBall": "3"},
  {"pokemon": "ホルビー", "needAllBall": "3"},
  {"pokemon": "マーイーカ", "needAllBall": "3"},
  {"pokemon": "マッギョ", "needAllBall": "3"},
  {"pokemon": "マホミル", "needAllBall": "2"},
  {"pokemon": "マメパト", "needAllBall": "3"},
  {"pokemon": "マラカッチ", "needAllBall": "3"},
  {"pokemon": "マンタイン", "needAllBall": "3"},
  {"pokemon": "ミツハニー", "needAllBall": "3"},
  {"pokemon": "ミブリム", "needAllBall": "2"},
  {"pokemon": "ミミッキュ", "needAllBall": "3"},
  {"pokemon": "ムンナ", "needAllBall": "3"},
  {"pokemon": "モグリュー", "needAllBall": "3"},
  {"pokemon": "モノズ", "needAllBall": "3"},
  {"pokemon": "モルペコ", "needAllBall": "3"},
  {"pokemon": "モンメン", "needAllBall": "3"},
  {"pokemon": "ヤクデ", "needAllBall": "3"},
  {"pokemon": "ヤジロン", "needAllBall": "0"},
  {"pokemon": "ヤトウモリ", "needAllBall": "3"},
  {"pokemon": "ヤバチャ", "needAllBall": "0"},
  {"pokemon": "ヤブクロン", "needAllBall": "3"},
  {"pokemon": "ヤミラミ", "needAllBall": "3"},
  {"pokemon": "ヤレユータン", "needAllBall": "3"},
  {"pokemon": "ヤンチャム", "needAllBall": "3"},
  {"pokemon": "ユキカブリ", "needAllBall": "3"},
  {"pokemon": "ユキハミ", "needAllBall": "3"},
  {"pokemon": "ユキワラシ", "needAllBall": "3"},
  {"pokemon": "ユニラン", "needAllBall": "3"},
  {"pokemon": "ヨーギラス", "needAllBall": "3"},
  {"pokemon": "ヨワマル", "needAllBall": "3"},
  {"pokemon": "ヨワシ", "needAllBall": "3"},
  {"pokemon": "ラクライ", "needAllBall": "3"},
  {"pokemon": "ラプラス", "needAllBall": "3"},
  {"pokemon": "ラルトス", "needAllBall": "3"},
  {"pokemon": "リオル", "needAllBall": "3"},
  {"pokemon": "リグレー", "needAllBall": "3"},
  {"pokemon": "ルチャブル", "needAllBall": "3"},
  {"pokemon": "ルナトーン", "needAllBall": "0"},
  {"pokemon": "ロコン", "needAllBall": "3"},
  {"pokemon": "ロゼリア", "needAllBall": "3"},
  {"pokemon": "ロトム", "needAllBall": "0"},
  {"pokemon": "ワシボン", "needAllBall": "1"},
  {"pokemon": "ワンパチ", "needAllBall": "3"},
  {"pokemon": "ワンリキー", "needAllBall": "3"}
]